exshll/__init__.py
exshll-0.0.1.data/scripts/foo
exshll-0.0.1.dist-info/LICENSE
exshll-0.0.1.dist-info/METADATA
exshll-0.0.1.dist-info/WHEEL
exshll-0.0.1.dist-info/top_level.txt
exshll-0.0.1.dist-info/RECORD
