Metadata-Version: 2.1
Name: exshll
Version: 0.0.1
Summary: xshll
Author: xxsaf
License: MIT
License-File: LICENSE
Requires-Dist: requests
